swaggercheck
