Metadata-Version: 2.1
Name: swagger-check
Version: 1.0.1.dev11
Summary: Validate API against its Swagger using Hypothesis
Home-page: https://github.com/adimian/swagger-check
Author: See AUTHORS
Author-email: eric@adimian.com
License: UNKNOWN
Platform: UNKNOWN
Classifier: Programming Language :: Python
Classifier: Programming Language :: Python :: 3.6
